[
    {
        "bdrc_id": "P3JT13450",
        "name": [
            {
                "bo": "བྱང་ཆུབ་སེངྒེ"
            }
        ],
        "alt_names": [
            [
                {
                    "bo": "བྱང་ཆུབ་སེངྒེ"
                }
            ],
            [
                {
                    "bo": "བྱང་ཆུབ་སེངྒེ"
                }
            ]
        ]
    },
    {
        "bdrc_id": "P9708",
        "name": [
            {
                "bo": "ཟུར་མང་དྲུང་པ ༡༠་ཀརྨ་ཆོས་ཀྱི་ཉིན་བྱེད།"
            }
        ],
        "alt_names": [
            [
                {
                    "bo": "ཟུར་མང་དྲུང་པ ༡༠"
                }
            ],
            [
                {
                    "bo": "སྒྲུབ་བརྒྱུད་བསྟན་འཛིན་ཆོས་ཀྱི་ཉི་མ།"
                }
            ],
            [
                {
                    "bo": "ཟུར་མང་དྲུང་པ ༡༠་ཀརྨ་ཆོས་ཀྱི་ཉིན་བྱེད།"
                }
            ],
            [
                {
                    "bo-x-phon-en-m-tbrc": "Zurmang Trungpa 10"
                }
            ],
            [
                {
                    "bo": "ཀརྨ་ཆོས་ཀྱི་ཉིན་བྱེད།"
                }
            ]
        ]
    },
    {
        "bdrc_id": "P9749",
        "name": [
            {
                "bo": "ཐེ་བོ་ལུང་བཟང་ནང་པ ༠༦་འགྱུར་མེད་ཐུབ་བསྟན་རྒྱ་མཚོ།"
            }
        ],
        "alt_names": [
            [
                {
                    "bo": "ཐེ་བོ་ལུང་བཟང་ནང་པ ༠༦་འགྱུར་མེད་ཐུབ་བསྟན་རྒྱ་མཚོ།"
                }
            ],
            [
                {
                    "bo-x-phon-en-m-tbrc": "Tewo Lungzang Nangpa 06"
                }
            ],
            [
                {
                    "bo": "འགྱུར་མེད་ཐུབ་བསྟན་རྒྱ་མཚོ།"
                }
            ],
            [
                {
                    "bo": "ཐེ་བོ་ལུང་བཟང་ནང་པ ༠༦"
                }
            ]
        ]
    },
    {
        "bdrc_id": "P2JM502",
        "name": [
            {
                "bo": "གླིང་མདའ་ནོར་ཁོ།"
            }
        ],
        "alt_names": [
            [
                {
                    "bo": "གླིང་མདའ་ནོར་ཁོ།"
                }
            ]
        ]
    },
    {
        "bdrc_id": "P9KT18",
        "name": [
            {
                "bo": "གསང་ཡུམ་ཇོ་མོ་ལྷ་སྐྱིད།"
            }
        ],
        "alt_names": [
            [
                {
                    "bo": "ཇོ་མོ་ལྷ་སྐྱིད།"
                }
            ]
        ]
    },
    {
        "bdrc_id": "P1713",
        "name": [
            {
                "bo": "བསམ་གཏན་ཚེ་རིང་།"
            }
        ],
        "alt_names": [
            [
                {
                    "bo": "བསམ་གཏན་ཚེ་རིང་།"
                }
            ]
        ]
    },
    {
        "bdrc_id": "P2LS304",
        "name": [
            {
                "bo": "ཚེ་རིང་དབྱངས་འཛོམ།"
            }
        ],
        "alt_names": [
            [
                {
                    "bo": "ཚེ་རིང་དབྱངས་འཛོམ།"
                }
            ]
        ]
    },
    {
        "bdrc_id": "P1KG26077",
        "name": [
            {
                "bo": "དཔྱི་ས་དྲུང་ཆེན་དཀོན་མཆོག་བསྟན་འཛིན་རྒྱ་མཚོ།"
            }
        ],
        "alt_names": [
            [
                {
                    "bo": "དཀོན་མཆོག་བསྟན་འཛིན་རྒྱ་མཚོ།"
                }
            ],
            [
                {
                    "bo": "དཔྱི་ས་དྲུང་ཆེན་སྤྲུལ་སྐུ་དཀོན་མཆོག་བསྟན་འཛིན་རྒྱ་མཚོ།"
                }
            ],
            [
                {
                    "bo": "དཔྱི་ས་དྲུང་ཆེན་དཀོན་མཆོག་བསྟན་འཛིན་རྒྱ་མཚོ།"
                }
            ]
        ]
    },
    {
        "bdrc_id": "P0AT0412",
        "name": [
            {
                "bo": "སློབ་དཔོན་ཞི་བའི་ཡེ་ཤེས།"
            },
            {
                "sa-x-iast": "*Sāntijñāna"
            }
        ],
        "alt_names": [
            [
                {
                    "bo": "སློབ་དཔོན་ཞི་བའི་ཡེ་ཤེས།"
                }
            ]
        ]
    },
    {
        "bdrc_id": "P8LS15126",
        "name": [
            {
                "bo": "འདུལ་འཛིན་བསོད་ནམས་བཟང་པོ།"
            }
        ],
        "alt_names": [
            [
                {
                    "bo": "འདུལ་འཛིན་བསོད་ནམས་བཟང་པོ།"
                }
            ],
            [
                {
                    "bo": "བསོད་ནམས་བཟང་པོ།"
                }
            ]
        ]
    },
    {
        "bdrc_id": "P1573",
        "name": [
            {
                "bo": "ཁྲི ༢༢་དགེ་འདུན་བསྟན་པ་དར་རྒྱས།"
            }
        ],
        "alt_names": [
            [
                {
                    "bo": "དགེ་འདུན་བསྟན་པ་དར་རྒྱས།"
                }
            ],
            [
                {
                    "bo": "ཀླུང་ཤོད་དགེ་འདུན་བསྟན་པ་དར་རྒྱས།"
                }
            ],
            [
                {
                    "bo": "མཁས་གྲུབ་དགེ་འདུན་བསྟན་པ་དར་རྒྱས།"
                }
            ],
            [
                {
                    "bo": "ཁྲི ༢༢་དགེ་འདུན་བསྟན་པ་དར་རྒྱས།"
                }
            ],
            [
                {
                    "bo": "དགའ་ལྡན་ཁྲི་པ ༢༢"
                }
            ]
        ]
    },
    {
        "bdrc_id": "P3260",
        "name": [
            {
                "bo": "སློབ་དཔོན་དབུ་བ་བློ་ལྡན།"
            },
            {
                "sa-x-iast": "Bhūvācārtya"
            }
        ],
        "alt_names": [
            [
                {
                    "bo": "བློ་ལྡན་རྗེ།"
                }
            ],
            [
                {
                    "bo": "སློབ་དཔོན་དབུ་བ་བློ་ལྡན།"
                }
            ],
            [
                {
                    "bo": "བྷུ་པ་བློ་ལྡན།"
                }
            ],
            [
                {
                    "bo": "སློབ་དཔོན་དབུ་བ།"
                }
            ],
            [
                {
                    "bo": "དབུས་པ་བློ་ལྡན།"
                }
            ]
        ]
    },
    {
        "bdrc_id": "P8LS4339",
        "name": [
            {
                "bo": "ལྷ་བྱམས་པ་རབ་བརྟན།"
            }
        ],
        "alt_names": [
            [
                {
                    "bo": "ལྷ་བྱམས་པ་རབ་བརྟན།"
                }
            ],
            [
                {
                    "bo": "བྱམས་པ་རབ་བརྟན།"
                }
            ],
            [
                {
                    "bo": "ཨེ་ལྷ་རྒྱ་རི་ཁྲིག་ཐོག ༠༦་བྱམས་པ་རབ་བརྟན།"
                }
            ]
        ]
    },
    {
        "bdrc_id": "P5618",
        "name": [
            {
                "bo": "རྒྱ་སྤྲུལ་བློ་བཟང་ཚེ་བརྟན་རྒྱལ་མཚན།"
            }
        ],
        "alt_names": [
            [
                {
                    "bo": "བློ་བཟང་ཚེ་བརྟན་རྒྱལ་མཚན།"
                }
            ],
            [
                {
                    "bo": "རྒྱ་སྤྲུལ་བློ་བཟང་ཚེ་བརྟན་རྒྱལ་མཚན།"
                }
            ]
        ]
    },
    {
        "bdrc_id": "P1TLMTGA000062",
        "name": [
            {
                "bo": "ལེགས་རྕོམ་སྙིང་བསྡུས།"
            }
        ],
        "alt_names": [
            [
                {
                    "bo": "ལེགས་རྕོམ་སྙིང་བསྡུས།"
                }
            ]
        ]
    },
    {
        "bdrc_id": "P1KG15487",
        "name": [
            {
                "bo": "སུའུ་ཅ་ཧོར།"
            },
            {
                "zh-Hans": "苏嘉宏"
            }
        ],
        "alt_names": [
            [
                {
                    "zh-Hans": "苏嘉宏"
                }
            ],
            [
                {
                    "bo": "སུའུ་ཅ་ཧོར།"
                }
            ]
        ]
    },
    {
        "bdrc_id": "P4CZ15257",
        "name": [
            {
                "bo": "སློབ་དཔོན་རྒྱལ་བས་བྱིན།"
            },
            {
                "sa-x-iast": "*Jinadatta"
            }
        ],
        "alt_names": [
            [
                {
                    "bo": "བསོད་སྙོམས་པ་རྒྱལ་བས་བྱིན།"
                }
            ],
            [
                {
                    "bo": "རྒྱལ་བས་བྱིན།"
                }
            ],
            [
                {
                    "bo": "སློབ་དཔོན་རྒྱལ་བས་བྱིན།"
                }
            ]
        ]
    },
    {
        "bdrc_id": "P7916",
        "name": [
            {
                "bo": "གཏེར་སྟོན ༠༤་དབང་ཆེན་དགྱེས་པའི་རྡོ་རྗེ།"
            }
        ],
        "alt_names": [
            [
                {
                    "bo": "དབང་ཆེན་དགྱེས་པའི་རྡོ་རྗེ།"
                }
            ],
            [
                {
                    "bo": "གཏེར་སྟོན ༠༤་དབང་ཆེན་དགྱེས་པའི་རྡོ་རྗེ།"
                }
            ]
        ]
    },
    {
        "bdrc_id": "P1883",
        "name": [
            {
                "bo": "རྒྱ་གར་བ་ཤེས་རབ་རྒྱལ་མཚན།"
            }
        ],
        "alt_names": [
            [
                {
                    "bo": "ས་སྐྱ་ཁྲི་འཛིན ༢༠"
                }
            ],
            [
                {
                    "bo": "ཤེས་རབ་རྒྱལ་མཚན།"
                }
            ],
            [
                {
                    "bo": "ས་སྐྱ་ཁྲི་ཆེན ༢༠"
                }
            ],
            [
                {
                    "bo": "རྒྱ་དཀར་ཤེས་རབ་རྒྱལ་མཚན་དཔལ་བཟང་པོ།"
                }
            ],
            [
                {
                    "bo": "རྒྱ་གར་བ་ཤེས་རབ་རྒྱལ་མཚན།"
                }
            ],
            [
                {
                    "bo": "ས་སྐྱ་བདག་ཆེན་ཤེས་རབ་རྒྱལ་མཚན།"
                }
            ],
            [
                {
                    "bo": "ས་སྐྱ་གོང་མ།"
                }
            ]
        ]
    },
    {
        "bdrc_id": "P10379",
        "name": [
            {
                "bo": "རི་རྒྱ་བསམ་གཏན་གླིང་སྤྲུལ་སྐུའི་སྐྱེ་བརྒྱུད།"
            }
        ],
        "alt_names": [
            [
                {
                    "bo": "རི་རྒྱ་བསམ་གཏན་གླིང་སྤྲུལ་སྐུའི་སྐྱེ་བརྒྱུད།"
                }
            ],
            [
                {
                    "bo": "བསམ་གཏན་གླིང་སྤྲུལ་སྐུའི་སྐྱེ་བརྒྱུད ༼རི་རྒྱ༽"
                }
            ]
        ]
    },
    {
        "bdrc_id": "P415",
        "name": [
            {
                "bo": "རྭ་ལོ་སྤྲུལ་སྐུ་བློ་བཟང་བསམ་གྲུབ།"
            }
        ],
        "alt_names": [
            [
                {
                    "bo": "བྱ་ཁྱུང་མཁན་རབས ༢༦་བློ་བཟང་བསམ་གྲུབ།"
                }
            ],
            [
                {
                    "bo": "རྭ་ལོ་སྤྲུལ་སྐུ་བློ་བཟང་བསམ་གྲུབ།"
                }
            ],
            [
                {
                    "bo": "བློ་བཟང་བསམ་གྲུབ།"
                }
            ],
            [
                {
                    "bo": "བྱ་ཁྱུང་མཁན་རབས ༢༦"
                }
            ]
        ]
    },
    {
        "bdrc_id": "P2050",
        "name": [
            {
                "bo": "གཙུག་ཏོར་སྐྱབས།"
            }
        ],
        "alt_names": [
            [
                {
                    "bo": "གཙུག་ཏོར་སྐྱབས།"
                }
            ]
        ]
    },
    {
        "bdrc_id": "P2AG20",
        "name": [
            {
                "bo": "ཆོས་དཔལ་བཟང་པོ།"
            }
        ],
        "alt_names": [
            [
                {
                    "bo": "ཆོས་དཔལ་བཟང་པོ།"
                }
            ],
            [
                {
                    "bo": "ཧང་རི་དཀའ་བཅུ་ཆོས་དཔལ་བཟང་པོ།"
                }
            ]
        ]
    },
    {
        "bdrc_id": "P0RK1194",
        "name": [
            {
                "bo": "ཚངས་པའི་རྒྱལ་པོ་གདོང་གསུམ་པ།"
            }
        ],
        "alt_names": [
            [
                {
                    "bo": "ཚངས་པའི་རྒྱལ་པོ་གདོང་གསུམ་པ།"
                }
            ]
        ]
    },
    {
        "bdrc_id": "P5384",
        "name": [
            {
                "bo": "དཀོན་མཆོག་ངེས་དོན་ཆོས་བསྒྲགས་རྒྱ་མཚོ།"
            }
        ],
        "alt_names": [
            [
                {
                    "bo": "དཀོན་མཆོག་ངེས་དོན་ཆོས་བསྒྲགས་རྒྱ་མཚོ།"
                }
            ],
            [
                {
                    "bo": "ཆོས་བསྒྲགས་རྒྱ་མཚོ,་དཀོན་མཆོག་ངེས་དོན།"
                }
            ]
        ]
    },
    {
        "bdrc_id": "P1113",
        "name": [
            {
                "bo": "གྲུབ་དབང་བློ་བཟང་ཚེ་འཕེལ།"
            }
        ],
        "alt_names": [
            [
                {
                    "bo": "བློ་བཟང་ཚེ་འཕེལ།"
                }
            ],
            [
                {
                    "bo": "གྲུབ་དབང་བློ་བཟང་ཚེ་འཕེལ།"
                }
            ]
        ]
    },
    {
        "bdrc_id": "P2JM292",
        "name": [
            {
                "bo": "དཔལ་སྤུངས་དབོན་སྤྲུལ།"
            }
        ],
        "alt_names": [
            [
                {
                    "bo": "དཔལ་སྤུངས་དབོན་སྤྲུལ།"
                }
            ]
        ]
    },
    {
        "bdrc_id": "P8LS75296",
        "name": [
            {
                "bo": "སངས་རྒྱས་དོན་འགྱུབ།"
            }
        ],
        "alt_names": [
            [
                {
                    "bo": "སངས་རྒྱས་དོན་འགྱུབ།"
                }
            ]
        ]
    },
    {
        "bdrc_id": "P1TLMTGA000100",
        "name": [
            {
                "bo": "དབྱངས་ཅན།"
            }
        ],
        "alt_names": [
            [
                {
                    "bo": "དབྱངས་ཅན།"
                }
            ]
        ]
    },
    {
        "bdrc_id": "P8LS13693",
        "name": [
            {
                "bo": "བིཀྵ་ཏ་དེ་ཝ།"
            }
        ],
        "alt_names": [
            [
                {
                    "bo": "བིཀྵ་ཏ་དེ་ཝ།"
                }
            ],
            [
                {
                    "bo": "བི་ཁྱ་ཏ།"
                }
            ]
        ]
    },
    {
        "bdrc_id": "P7100",
        "name": [
            {
                "bo": "སྐལ་བཟང་འཕེལ་རྒྱས།"
            }
        ],
        "alt_names": [
            [
                {
                    "bo": "སྐལ་བཟང་འཕེལ་རྒྱས།"
                }
            ]
        ]
    },
    {
        "bdrc_id": "P862",
        "name": [
            {
                "bo": "བྱང་ཆུབ་བརྩོན་འགྲུས།"
            }
        ],
        "alt_names": [
            [
                {
                    "bo": "བྱང་ཆུབ་བརྩོན་འགྲུས།"
                }
            ],
            [
                {
                    "bo": "འབྲུག་པ་བྱང་ཆུབ་བརྩོན་འགྲུས།"
                }
            ]
        ]
    },
    {
        "bdrc_id": "P4CN12048",
        "name": [
            {
                "bo": "ནོར་བུ་ལྷ་སྐྱིད།"
            }
        ],
        "alt_names": [
            [
                {
                    "bo": "ནོར་བུ་ལྷ་སྐྱིད།"
                }
            ],
            [
                {
                    "bo": "སྟོང་ཉིད་མ།"
                }
            ]
        ]
    },
    {
        "bdrc_id": "P3457",
        "name": [
            {
                "bo": "ལྷ་བླ་མ་བྱང་ཆུབ་འོད།"
            }
        ],
        "alt_names": [
            [
                {
                    "bo": "བྱང་ཆུབ་འོད།"
                }
            ],
            [
                {
                    "bo": "ལྷ་བླ་མ་བྱང་ཆུབ་འོད།"
                }
            ]
        ]
    },
    {
        "bdrc_id": "P6481",
        "name": [
            {
                "bo": "ཨ་སྐྱོང་བླ་མ་ངག་དབང་དཀོན་མཆོག་རྒྱ་མཚོ།"
            }
        ],
        "alt_names": [
            [
                {
                    "bo": "ངག་དབང་དཀོན་མཆོག་རྒྱ་མཚོ།"
                }
            ],
            [
                {
                    "bo": "ཨ་སྐྱོང་བླ་མ་ངག་དབང་དཀོན་མཆོག་རྒྱ་མཚོ།"
                }
            ]
        ]
    },
    {
        "bdrc_id": "P8923",
        "name": [
            {
                "bo": "དྲུང་པ ༠༢་རིན་ཆེན་བཟང་པོ།"
            }
        ],
        "alt_names": [
            [
                {
                    "bo-x-phon-en-m-tbrc": "Trungpa 02"
                }
            ],
            [
                {
                    "bo": "དྲུང་པ ༠༢་རིན་ཆེན་བཟང་པོ།"
                }
            ],
            [
                {
                    "bo": "དྲུང་པ ༠༢"
                }
            ],
            [
                {
                    "bo": "རིན་ཆེན་བཟང་པོ།"
                }
            ]
        ]
    },
    {
        "bdrc_id": "P7156",
        "name": [
            {
                "bo": "ས་ཕུག་པ་ཤཱཀྱ་རྡོ་རྗེ།"
            },
            {
                "sa-x-ewts": "shAkya badz+ra"
            }
        ],
        "alt_names": [
            [
                {
                    "sa-x-ewts": "shAkya badz+ra"
                }
            ],
            [
                {
                    "bo": "ཁམས་པ་ས་ཕུག་པ་ཤཱཀྱ་རྡོ་རྗེ།"
                }
            ],
            [
                {
                    "bo": "ས་ཕུག་པ་ཤཱཀྱ་རྡོ་རྗེ།"
                }
            ],
            [
                {
                    "bo": "ཤཱཀྱ་རྡོ་རྗེ།"
                }
            ]
        ]
    },
    {
        "bdrc_id": "P1KG5849",
        "name": [
            {
                "bo": "ཞེ་ལུད།"
            }
        ],
        "alt_names": [
            [
                {
                    "bo": "ཞེ་ལུད།"
                }
            ]
        ]
    },
    {
        "bdrc_id": "P8LS75444",
        "name": [
            {
                "bo": "སྤུ་ཧྲེང་ཁྲི་རྒྱལ་རྟེན་འབྲེལ་བཟང་མོ།"
            }
        ],
        "alt_names": [
            [
                {
                    "bo": "སྤུ་ཧྲེང་ཁྲི་རྒྱལ་རྟེན་འབྲེལ་བཟང་མོ།"
                }
            ],
            [
                {
                    "bo": "རྟེན་འབྲེལ་བཟང་མོ།"
                }
            ]
        ]
    },
    {
        "bdrc_id": "P3416",
        "name": [
            {
                "bo": "བློ་གྲོས་འོད་ཟེར།"
            }
        ],
        "alt_names": [
            [
                {
                    "bo": "བློ་གྲོས་འོད་ཟེར།"
                }
            ],
            [
                {
                    "bo": "གྲུབ་དབང་བློ་གྲོས་འོད་ཟེར།"
                }
            ]
        ]
    },
    {
        "bdrc_id": "P8LS13780",
        "name": [
            {
                "bo": "ཚུལ་ཁྲིམས་འབུམ།"
            }
        ],
        "alt_names": [
            [
                {
                    "bo": "ཚུལ་ཁྲིམས་འབུམ།"
                }
            ],
            [
                {
                    "bo": "འགྲོ་མགོན་ཤངས་སྟོན་ཚུལ་ཁྲིམས་འབུམ།"
                }
            ]
        ]
    },
    {
        "bdrc_id": "P8LS75307",
        "name": [
            {
                "bo": "ཚེ་མོ་སྐྱིད།"
            }
        ],
        "alt_names": [
            [
                {
                    "bo": "ཚེ་མོ་སྐྱིད།"
                }
            ]
        ]
    },
    {
        "bdrc_id": "P8LS15526",
        "name": [
            {
                "bo": "འགོས་ཚུལ་ཁྲིམས་བྱང་ཆུབ།"
            }
        ],
        "alt_names": [
            [
                {
                    "bo": "འགོས་ཚུལ་བྱང་།"
                }
            ],
            [
                {
                    "bo": "ཚུལ་ཁྲིམས་བྱང་ཆུབ།"
                }
            ],
            [
                {
                    "bo": "འགོས་ཚུལ་ཁྲིམས་བྱང་ཆུབ།"
                }
            ]
        ]
    },
    {
        "bdrc_id": "P14",
        "name": [
            {
                "bo": "འབྲུག་རྗེ་མཁན་པོ ༠༡་པད་དཀར་འབྱུང་གནས།"
            }
        ],
        "alt_names": [
            [
                {
                    "bo": "འབྲུག་རྗེ་མཁན་པོ ༠༡"
                }
            ],
            [
                {
                    "bo": "འབྲུག་རྗེ་མཁན་པོ ༠༡་པད་དཀར་འབྱུང་གནས།"
                }
            ],
            [
                {
                    "bo": "པད་དཀར་འབྱུང་གནས།"
                }
            ]
        ]
    },
    {
        "bdrc_id": "P6136",
        "name": [
            {
                "bo": "ཨ་ཧཱུཾ་རྒྱན།"
            }
        ],
        "alt_names": [
            [
                {
                    "bo": "ཨ་ཧཱུཾ་རྒྱན།"
                }
            ]
        ]
    },
    {
        "bdrc_id": "P3321",
        "name": [
            {
                "bo": "རྟོགས་ལྡན་སངས་རྒྱས་དགེ་སློང་།"
            }
        ],
        "alt_names": [
            [
                {
                    "bo": "རྟོགས་ལྡན་སངས་རྒྱས་དགེ་སློང་།"
                }
            ],
            [
                {
                    "bo": "སངས་རྒྱས་དགེ་སློང་།"
                }
            ]
        ]
    },
    {
        "bdrc_id": "P5021",
        "name": [
            {
                "bo": "དཔལ་སྤུངས་སྨན་པ་ཆོས་འབྱོར་རྒྱ་མཚོ།"
            }
        ],
        "alt_names": [
            [
                {
                    "bo": "དཔལ་སྤུངས་སྨན་པ་ཆོས་འབྱོར་རྒྱ་མཚོ།"
                }
            ],
            [
                {
                    "bo": "ཆོས་འབྱོར་རྒྱ་མཚོ།"
                }
            ]
        ]
    },
    {
        "bdrc_id": "P1598",
        "name": [
            {
                "bo": "སློབ་དཔོན་བཟོད་པ་དཔལ།"
            }
        ],
        "alt_names": [
            [
                {
                    "bo": "བཟོད་པ་དཔལ།"
                }
            ],
            [
                {
                    "bo": "སློབ་དཔོན་བཟོད་པ་དཔལ།"
                }
            ]
        ]
    },
    {
        "bdrc_id": "P4PD1497",
        "name": [
            {
                "bo": "ཚུལ་ཁྲིམས་འོད་ཟེར།"
            }
        ],
        "alt_names": [
            [
                {
                    "bo": "མངའ་རིས་རབ་འབྱམས་པ་ཚུལ་ཁྲིམས་འོད་ཟེར།"
                }
            ],
            [
                {
                    "bo": "ཚུལ་ཁྲིམས་འོད་ཟེར།"
                }
            ]
        ]
    },
    {
        "bdrc_id": "P9983",
        "name": [
            {
                "bo": "མངའ་རིས་པ་ཚུལ་དབང་ཤེས་རབ།"
            }
        ],
        "alt_names": [
            [
                {
                    "bo": "མངའ་རིས་པ་ཚུལ་དབང་ཤེས་རབ།"
                }
            ],
            [
                {
                    "bo": "ཚུལ་དབང་ཤེས་རབ།"
                }
            ]
        ]
    },
    {
        "bdrc_id": "P1TLMTGA000071",
        "name": [
            {
                "bo": "ལེགས་རྕོམ་སྙིང་བསྡུས།"
            }
        ],
        "alt_names": [
            [
                {
                    "bo": "ལེགས་རྕོམ་སྙིང་བསྡུས།"
                }
            ]
        ]
    },
    {
        "bdrc_id": "P2JM137",
        "name": [
            {
                "bo": "འབུམ་འབར།"
            }
        ],
        "alt_names": [
            [
                {
                    "bo": "འབུམ་འབར།"
                }
            ]
        ]
    },
    {
        "bdrc_id": "P2CZ7890",
        "name": [
            {
                "bo": "མངའ་རིས་གུང་ཐང་ཆོས་རྒྱལ་ཁྲི་བསོད་ནམས་ལྡེ།"
            }
        ],
        "alt_names": [
            [
                {
                    "bo": "ཁྲི་བསྡོད་ནམས་ལྡེ།"
                }
            ],
            [
                {
                    "bo": "མངའ་རིས་གུང་ཐང་ཆོས་རྒྱལ་ཁྲི་བསོད་ནམས་ལྡེ།"
                }
            ]
        ]
    },
    {
        "bdrc_id": "P3KG73",
        "name": [
            {
                "bo": "ཀརྨ་ཚེ་རིང་།"
            }
        ],
        "alt_names": [
            [
                {
                    "bo": "ཀརྨ་ཚེ་རིང་།"
                }
            ]
        ]
    },
    {
        "bdrc_id": "P1TLMTGA001181",
        "name": [
            {
                "bo": "རྒྱལ་མཚན།"
            }
        ],
        "alt_names": [
            [
                {
                    "bo": "རྒྱལ་མཚན།"
                }
            ]
        ]
    },
    {
        "bdrc_id": "P8LS76441",
        "name": [
            {
                "bo": "ཨ་ནེ་འཕྲིན་ལས་ཆོས་སྒྲོན།"
            },
            {
                "en": "Ani Trinle Chodron"
            }
        ],
        "alt_names": [
            [
                {
                    "en": "Ani Trinle Chodron"
                }
            ],
            [
                {
                    "bo": "ཨ་ནེ་འཕྲིན་ལས་ཆོས་སྒྲོན།"
                }
            ],
            [
                {
                    "bo": "འཕྲིན་ལས་ཆོས་སྒྲོན།"
                }
            ]
        ]
    },
    {
        "bdrc_id": "P2KG228822",
        "name": [
            {
                "bo": "སྐལ་བཟང་དབང་ཕྱུག"
            },
            {
                "en": "kalsang wangchuk"
            }
        ],
        "alt_names": [
            [
                {
                    "bo": "སྐལ་བཟང་དབང་ཕྱུག"
                }
            ],
            [
                {
                    "en": "kalsang wangchuk"
                }
            ]
        ]
    },
    {
        "bdrc_id": "P5515",
        "name": [
            {
                "bo": "ཁམས་པ་རོ་མཉམ་རྡོ་རྗེ།"
            }
        ],
        "alt_names": [
            [
                {
                    "bo": "ཁམས་པ་རོ་མཉམ་རྡོ་རྗེ།"
                }
            ],
            [
                {
                    "bo": "རོ་མཉམ་རྡོ་རྗེ།"
                }
            ]
        ]
    },
    {
        "bdrc_id": "P1043",
        "name": [
            {
                "bo": "བོད་མཁས་པ་མི་ཕམ་དགེ་ལེགས་རྣམ་རྒྱལ།"
            }
        ],
        "alt_names": [
            [
                {
                    "bo": "སྙེ་སྨན་ཆེན་པོ།"
                }
            ],
            [
                {
                    "bo": "བོད་མཁས་པ་མི་ཕམ་དགེ་ལེགས་རྣམ་རྒྱལ།"
                }
            ],
            [
                {
                    "bo": "དགེ་ལེགས་རྣམ་རྒྱལ།"
                }
            ],
            [
                {
                    "bo": "མི་ཕམ་དགེ་ལེགས་རྣམ་རྒྱལ།"
                }
            ],
            [
                {
                    "bo": "ལྷ་རྗེ་སྙེ་སྨན་ཆེན་པོ།"
                }
            ]
        ]
    },
    {
        "bdrc_id": "P772",
        "name": [
            {
                "bo": "ཡོངས་འཛིན་བློ་གྲོས་རིན་ཆེན།"
            }
        ],
        "alt_names": [
            [
                {
                    "bo": "བློ་གྲོས་རིན་ཆེན།"
                }
            ],
            [
                {
                    "bo": "ཡོངས་འཛིན་བློ་གྲོས་རིན་ཆེན།"
                }
            ]
        ]
    },
    {
        "bdrc_id": "P6285",
        "name": [
            {
                "bo": "ལང་དཔའ་ཐའི་སྤྲུལ་སྐུ་བསྟན་འཛིན་མཁས་བཙུན་དཔལ་བཟང་།"
            }
        ],
        "alt_names": [
            [
                {
                    "bo": "ལང་དཔའ་ཐའི་སྤྲུལ་སྐུ་བསྟན་འཛིན་མཁས་བཙུན་དཔལ་བཟང་།"
                }
            ],
            [
                {
                    "bo": "བསྟན་འཛིན་མཁས་བཙུན་དཔལ་བཟང་།"
                }
            ]
        ]
    },
    {
        "bdrc_id": "P3394",
        "name": [
            {
                "bo": "རི་ཀླུང་ཕུག་པ་ཆོས་དགོན།"
            }
        ],
        "alt_names": [
            [
                {
                    "bo": "ཆོས་དགོན་རི་ཀླུང་ཕུག་པ།"
                }
            ],
            [
                {
                    "bo": "ཕུག་པ་ཆོས་དགོན།"
                }
            ],
            [
                {
                    "bo": "རི་ཀླུང་ཕུག་པ་ཆོས་དགོན།"
                }
            ]
        ]
    },
    {
        "bdrc_id": "P1649",
        "name": [
            {
                "bo": "ཏཱ་ལའི་བླ་མ ༡༤་བསྟན་འཛིན་རྒྱ་མཚོ།"
            },
            {
                "en": "His Holiness the Dalai Lama 14 Tendzin Gyatso"
            }
        ],
        "alt_names": [
            [
                {
                    "bo": "རྒྱལ་བ་བསྟན་འཛིན་རྒྱ་མཚོ།"
                }
            ],
            [
                {
                    "bo": "ཏཱ་ལའི་བླ་མ ༡༤"
                }
            ],
            [
                {
                    "en": "His Holiness the Dalai Lama 14 Tendzin Gyatso"
                }
            ],
            [
                {
                    "bo": "སྐུ་ཕྲེང་བཅུ་བཞི་པ་ཆེན་པོ།"
                }
            ],
            [
                {
                    "bo": "ཏཱ་ལའི་བླ་མ ༡༤"
                }
            ],
            [
                {
                    "bo": "བསྟན་འཛིན་རྒྱ་མཚོ།"
                }
            ],
            [
                {
                    "bo-x-phon-en-m-tbrc": "Dalai Lama 14"
                }
            ],
            [
                {
                    "bo": "ཏཱ་ལའི་བླ་མ ༡༤་བསྟན་འཛིན་རྒྱ་མཚོ།"
                }
            ],
            [
                {
                    "bo": "གོང་ས་སྐྱབས་མགོན་ཏཱ་ལའི་བླ་མ་བསྟན་འཛིན་རྒྱ་མཚོ།"
                }
            ]
        ]
    },
    {
        "bdrc_id": "P4728",
        "name": [
            {
                "bo": "ཐོ་ཡོན་བླ་མ ༣"
            }
        ],
        "alt_names": [
            [
                {
                    "bo": "ཐོ་ཡོན་བླ་མ ༣"
                }
            ],
            [
                {
                    "bo": "བློ་བཟང་བསྟན་པ་རབ་རྒྱས།"
                }
            ],
            [
                {
                    "bo": "ཐོ་ཡོན ༣་བློ་བཟང་བསྟན་པ་རབ་རྒྱས།"
                }
            ]
        ]
    },
    {
        "bdrc_id": "P2DB19542",
        "name": [
            {
                "bo": "རྡོ་རྗེ་དགྲ་འདུལ།"
            }
        ],
        "alt_names": [
            [
                {
                    "bo": "རྡོར་ལོ།"
                }
            ],
            [],
            [
                {
                    "bo": "རྡོ་རྗེ་དགྲ་འདུལ།"
                }
            ],
            [
                {
                    "bo": "ཤཱཀྱ་རང་བྱུང་དགེ་ལེགས་ཡོན་ཏན་རྒྱ་མཚོ།"
                }
            ]
        ]
    },
    {
        "bdrc_id": "P2KG229171",
        "name": [
            {
                "bo": "མགོན་པོ་ཚེ་བརྟན།"
            }
        ],
        "alt_names": [
            [
                {
                    "bo": "མགོན་པོ་ཚེ་བརྟན།"
                }
            ]
        ]
    },
    {
        "bdrc_id": "P3413",
        "name": [
            {
                "bo": "གཉན་ཆེན་བསོད་ནམས་བརྟན་པ།"
            }
        ],
        "alt_names": [
            [
                {
                    "bo": "བསོད་ནམས་བརྟན་པ།"
                }
            ],
            [
                {
                    "bo": "ཉན་པོ་བསོད་ནམས་བརྟན་པ།"
                }
            ],
            [
                {
                    "bo": "ཉན་ཆེན་བསོད་ནམས་བརྟན་པ།"
                }
            ],
            [
                {
                    "bo": "གཉན་ཆེན་བསོད་ནམས་བརྟན་པ།"
                }
            ]
        ]
    },
    {
        "bdrc_id": "P1TLMTGA002247",
        "name": [
            {
                "bo": "སྦྲ་རིགས་ཐོགས་མེད།"
            }
        ],
        "alt_names": [
            [
                {
                    "bo": "སྦྲ་རིགས་ཐོགས་མེད།"
                }
            ]
        ]
    },
    {
        "bdrc_id": "P8LS15411",
        "name": [
            {
                "bo": "ཀུ་ཀུ་རཱ་ཛ་སྔོན་མ།"
            },
            {
                "sa-x-iast": "Kukurāja"
            }
        ],
        "alt_names": [
            [
                {
                    "bo": "ཀུ་ཀུ་རཱ་ཛ་སྔོན་མ།"
                }
            ],
            [
                {
                    "bo": "ཀུ་ཀུ་རཱ་ཛ།"
                }
            ],
            [
                {
                    "bo": "གུ་གུ་ར་ཙ྄"
                }
            ],
            [
                {
                    "bo": "ཁྱིའི་རྒྱལ་པ྄ོ"
                }
            ],
            [
                {
                    "bo": "ཀུ་ཀུ་ར་ཛ།"
                }
            ],
            [
                {
                    "sa-x-iast": "Kukkurarāja?"
                }
            ],
            [
                {
                    "sa-x-iast": "Kukura?"
                }
            ]
        ]
    },
    {
        "bdrc_id": "P5162",
        "name": [
            {
                "bo": "བདེ་ཆེན་ཆོས་འཁོར་ཡོངས་འཛིན ༠༨་ངག་གི་དབང་པོ།"
            }
        ],
        "alt_names": [
            [
                {
                    "bo-x-phon-en-m-tbrc": "Dechen Chokor Yongdzin 08"
                }
            ],
            [
                {
                    "bo": "བདེ་ཆེན་ཆོས་འཁོར་ཡོངས་འཛིན ༠༨"
                }
            ],
            [
                {
                    "bo": "བདེ་ཆེན་ཆོས་འཁོར་ཡོངས་འཛིན ༠༨་ངག་གི་དབང་པོ།"
                }
            ],
            [
                {
                    "bo": "ངག་གི་དབང་པོ།"
                }
            ]
        ]
    },
    {
        "bdrc_id": "P9696",
        "name": [
            {
                "bo": "རྩེ་དྲུག་བླ་མ་ཚུལ་ཁྲིམས་གྲགས་པ།"
            }
        ],
        "alt_names": [
            [
                {
                    "bo": "ཚུལ་ཁྲིམས་གྲགས་པ།"
                }
            ],
            [
                {
                    "bo": "རྩེ་དྲུག་བླ་མ་ཚུལ་ཁྲིམས་གྲགས་པ།"
                }
            ]
        ]
    },
    {
        "bdrc_id": "P1TLMTGA000935",
        "name": [
            {
                "bo": "ཀུན་དགའ་ཡོན་ཏན་ཆོས་བཟང་།"
            }
        ],
        "alt_names": [
            [
                {
                    "bo": "ཀུན་དགའ་ཡོན་ཏན་ཆོས་བཟང་།"
                }
            ]
        ]
    },
    {
        "bdrc_id": "P0AT0168",
        "name": [
            {
                "sa-x-iast": "Govardhana"
            }
        ],
        "alt_names": []
    },
    {
        "bdrc_id": "P8053",
        "name": [
            {
                "bo": "གཟིམ་གོང་སྨན་པ་ཚེ་བརྟན་ལྷ་དབང་།"
            }
        ],
        "alt_names": [
            [
                {
                    "bo": "གཟིམ་གོང་སྨན་པ་ཚེ་བརྟན་ལྷ་དབང་།"
                }
            ],
            [
                {
                    "bo": "ཚེ་བརྟན་ལྷ་དབང་།"
                }
            ]
        ]
    },
    {
        "bdrc_id": "P8LS12770",
        "name": [
            {
                "bo": "བློ་བཟང་ཚངས་དབྱངས་ཆོས་གྲགས་རྒྱ་མཚོ།"
            }
        ],
        "alt_names": [
            [
                {
                    "bo": "བློ་བཟང་ཚངས་དབྱངས་ཆོས་གྲགས་རྒྱ་མཚོ།"
                }
            ],
            [
                {
                    "bo-x-phon-en-m-tbrc": "Dungkar Tulku 06"
                }
            ],
            [
                {
                    "bo": "དུང་དཀར་སྤྲུལ་སྐུ ༠༦"
                }
            ]
        ]
    },
    {
        "bdrc_id": "P0RK746",
        "name": [
            {
                "bo": "ཆོས་རྗེ་བུདདྷ་བ།"
            }
        ],
        "alt_names": [
            [
                {
                    "bo": "ནམ་མཁའ་སངས་རྒྱས།"
                }
            ],
            [
                {
                    "bo": "རྗེ་ནམ་སངས།"
                }
            ],
            [
                {
                    "bo": "རྒྱལ་ཚབ་ག་ག་ན་བུདདྷ།"
                }
            ],
            [
                {
                    "bo": "རྗེ་ནམ་མཁའ་སངས་རྒྱས།"
                }
            ],
            [
                {
                    "bo": "ཆོས་རྗེ་བུདདྷ་བ།"
                }
            ],
            [
                {
                    "bo": "རྗེ་ག་ག་ན་བུདདྷ།"
                }
            ],
            [
                {
                    "bo": "མཁན་ཆེན་ནམ་མཁའ་སངས་རྒྱས།"
                }
            ]
        ]
    },
    {
        "bdrc_id": "P1161",
        "name": [
            {
                "bo": "དུང་དཀར་བློ་བཟང་འཕྲིན་ལས།"
            }
        ],
        "alt_names": [
            [
                {
                    "bo": "དུང་དཀར་རིན་པོ་ཆེ།"
                }
            ],
            [
                {
                    "bo": "དགེ་རྒན་ཆེན་མོ་བ།"
                }
            ],
            [
                {
                    "bo": "བློ་བཟང་འཕྲིན་ལས།"
                }
            ],
            [
                {
                    "bo": "བློ་བཟང་དགའ་ལྡན་འཕྲིན་ལས་རྒྱ་མཚོ།"
                }
            ],
            [
                {
                    "bo": "སེར་སྨད་དུང་དཀར་སྤྲུལ་སྐུ།"
                }
            ],
            [
                {
                    "bo": "དུང་དཀར་བློ་བཟང་འཕྲིན་ལས།"
                }
            ]
        ]
    },
    {
        "bdrc_id": "P2599",
        "name": [
            {
                "bo": "ཁྲོ་ཤུལ་བླ་མ་ངག་དབང་སྨིན་གྲོལ་རྒྱ་མཚོ།"
            }
        ],
        "alt_names": [
            [
                {
                    "bo": "ཁྲོ་ཤུལ་བླ་མ་ངག་དབང་སྨིན་གྲོལ་རྒྱ་མཚོ།"
                }
            ],
            [
                {
                    "bo": "ངག་དབང་སྨིན་གྲོལ་རྒྱ་མཚོ།"
                }
            ]
        ]
    },
    {
        "bdrc_id": "P0AT0295",
        "name": [
            {
                "bo": "གསེར་གླིང་རྒྱལ་པོ་དཔལ་ལྡན་ཆོས་སྐྱོང་།"
            },
            {
                "sa-x-iast": "Śrīdharmapāla"
            }
        ],
        "alt_names": [
            [
                {
                    "bo": "གསེར་གླིང་རྒྱལ་པོ་དཔལ་ལྡན་ཆོས་སྐྱོང་།"
                }
            ]
        ]
    },
    {
        "bdrc_id": "P6036",
        "name": [
            {
                "bo": "བྱ་བྲལ་སངས་རྒྱས་རྡོ་རྗེ།"
            }
        ],
        "alt_names": [
            [
                {
                    "bo": "སངས་རྒྱས་རྡོ་རྗེ།"
                }
            ],
            [
                {
                    "bo": "ཁྲོ་རྒྱལ་རྡོ་རྗེ།"
                }
            ],
            [
                {
                    "bo": "བྱ་བྲལ་སངས་རྒྱས་རྡོ་རྗེ།"
                }
            ]
        ]
    },
    {
        "bdrc_id": "P8LS15164",
        "name": [
            {
                "bo": "བསོད་ནམས་དབང་པོ།"
            }
        ],
        "alt_names": [
            [
                {
                    "bo": "ཉང་བསོད་ནམས་དབང་པོ།"
                }
            ],
            [
                {
                    "bo": "བསོད་ནམས་དབང་པོ།"
                }
            ]
        ]
    },
    {
        "bdrc_id": "P8LS15099",
        "name": [
            {
                "bo": "ཚུལ་ཁྲིམས་བཤེས་གཉེན།"
            },
            {
                "sa-x-ndia": "shI la mi tra"
            }
        ],
        "alt_names": [
            [
                {
                    "sa-x-ndia": "shI la mi tra"
                }
            ],
            [
                {
                    "bo": "ཚུལ་ཁྲིམས་བཤེས་གཉེན།"
                }
            ]
        ]
    },
    {
        "bdrc_id": "P2LS188",
        "name": [
            {
                "bo": "པ་སངས་ཚེ་རིང་།"
            }
        ],
        "alt_names": [
            [
                {
                    "bo": "པ་སངས་ཚེ་རིང་།"
                }
            ]
        ]
    },
    {
        "bdrc_id": "P00JR551",
        "name": [
            {
                "bo": "མཁན་བསྟན་འཛིན་བཟང་པོ།"
            }
        ],
        "alt_names": [
            [
                {
                    "bo": "བསྟན་འཛིན་བཟང་པོ།"
                }
            ],
            [
                {
                    "bo": "མཁན་བསྟན་འཛིན་བཟང་པོ།"
                }
            ]
        ]
    },
    {
        "bdrc_id": "P4CZ15097",
        "name": [
            {
                "bo": "པཎྜི་ཏ་ཇོ་བོ་རི་པ་ཇོ་བོ་རི་པ།"
            },
            {
                "sa-x-iast": "Skt?? Tib??"
            }
        ],
        "alt_names": [
            [
                {
                    "bo": "ཇོ་བོ་རི་པ།"
                }
            ],
            [
                {
                    "bo": "པཎྜི་ཏ་ཇོ་བོ་རི་པ་ཇོ་བོ་རི་པ།"
                }
            ]
        ]
    },
    {
        "bdrc_id": "P0RK1328",
        "name": [
            {
                "bo": "ཤེས་རབ་དཔལ་ལྡན།"
            }
        ],
        "alt_names": [
            [
                {
                    "bo": "ཤེས་རབ་དཔལ་ལྡན།"
                }
            ]
        ]
    }
]